sudogdz.py
sudogdz-1.0.2.dist-info/LICENSE
sudogdz-1.0.2.dist-info/WHEEL
sudogdz-1.0.2.dist-info/METADATA
sudogdz-1.0.2.dist-info/RECORD
