Metadata-Version: 2.1
Name: sudogdz
Version: 1.0.2
Summary: Parser of everything from the Russian reshebnik GDZ.RU
Author: aye20054925
Requires-Python: >=3.6
Classifier: Development Status :: 5 - Production/Stable
Classifier: Topic :: Internet
Classifier: Topic :: Internet :: WWW/HTTP :: Dynamic Content
Classifier: Topic :: Education
Classifier: Programming Language :: Python
Classifier: Programming Language :: Python :: 3.6
Classifier: Programming Language :: Python :: 3.7
Classifier: Programming Language :: Python :: 3.8
Classifier: Programming Language :: Python :: 3.9
Classifier: License :: OSI Approved :: MIT License
Requires-Dist: requests
Requires-Dist: beautifulsoup4
